<Properties StartupConfiguration="{9FDDBF35-9B60-497B-8B07-6AF151A85955}|Default">
  <MonoDevelop.Ide.ItemProperties.RESTRecipe.Android PreferredExecutionTarget="Android.Pixel_2_API_28" />
  <MonoDevelop.Ide.Workbench ActiveDocument="RESTRecipe/RESTRecipePage.xaml">
    <Files>
      <File FileName="RESTRecipe/RESTRecipePage.xaml" Line="1" Column="1" />
    </Files>
    <Pads>
      <Pad Id="ProjectPad">
        <State name="__root__">
          <Node name="RESTRecipe" expanded="True">
            <Node name="RESTRecipe" expanded="True">
              <Node name="RESTRecipePage.xaml" expanded="True" selected="True" />
            </Node>
          </Node>
        </State>
      </Pad>
    </Pads>
  </MonoDevelop.Ide.Workbench>
  <MonoDevelop.Ide.DebuggingService.PinnedWatches />
  <MonoDevelop.Ide.Workspace ActiveConfiguration="Debug" />
  <MonoDevelop.Ide.DebuggingService.Breakpoints>
    <BreakpointStore />
  </MonoDevelop.Ide.DebuggingService.Breakpoints>
  <MultiItemStartupConfigurations />
  <MonoDevelop.Ide.ItemProperties.RESTRecipe.iOS FirstBuild="True" />
</Properties>